onegov.directory-0.4.8-py3.6-nspkg.pth
onegov/directory/.gitignore
onegov/directory/__init__.py
onegov/directory/archive.py
onegov/directory/errors.py
onegov/directory/migration.py
onegov/directory/upgrade.py
onegov/directory/collections/__init__.py
onegov/directory/collections/directory.py
onegov/directory/collections/directory_entry.py
onegov/directory/models/__init__.py
onegov/directory/models/directory.py
onegov/directory/models/directory_entry.py
onegov/directory/tests/conftest.py
onegov/directory/tests/test_archive.py
onegov/directory/tests/test_migration.py
onegov/directory/tests/test_orm.py
onegov/directory/types/__init__.py
onegov/directory/types/directory_configuration.py
onegov.directory-0.4.8.dist-info/METADATA
onegov.directory-0.4.8.dist-info/WHEEL
onegov.directory-0.4.8.dist-info/entry_points.txt
onegov.directory-0.4.8.dist-info/namespace_packages.txt
onegov.directory-0.4.8.dist-info/top_level.txt
onegov.directory-0.4.8.dist-info/RECORD
