Metadata-Version: 2.1
Name: onegov.directory
Version: 0.4.8
Summary: Directories for the OneGov Cloud.
Home-page: http://github.com/OneGov/onegov.directory
Author: Seantis GmbH
Author-email: info@seantis.ch
License: GPLv2
Platform: any
Classifier: Intended Audience :: Developers
Classifier: Programming Language :: Python :: 3 :: Only
Classifier: Programming Language :: Python :: 3.4
Classifier: Programming Language :: Python :: 3.5
Classifier: Topic :: Software Development :: Libraries :: Python Modules
Classifier: License :: OSI Approved :: GNU General Public License v2 (GPLv2)
Requires-Python: >=3.6
Requires-Dist: more-itertools
Requires-Dist: onegov.core (>=0.4.0)
Requires-Dist: onegov.file
Requires-Dist: onegov.form (>=0.31.0)
Requires-Dist: onegov.gis
Requires-Dist: onegov.search
Requires-Dist: pyyaml
Provides-Extra: test
Requires-Dist: coverage ; extra == 'test'
Requires-Dist: onegov-testing ; extra == 'test'
Requires-Dist: pytest ; extra == 'test'
